jps2sm/__init__.py
jps2sm/batch.py
jps2sm/constants.py
jps2sm/get_data.py
jps2sm/jps2sm.py
jps2sm/mediainfo.py
jps2sm/myloginsession.py
jps2sm/prepare_data.py
jps2sm/save_data.py
jps2sm/upload_data.py
jps2sm/utils.py
jps2sm/validation.py
jps2sm-1.16.dist-info/COPYING
jps2sm-1.16.dist-info/METADATA
jps2sm-1.16.dist-info/WHEEL
jps2sm-1.16.dist-info/entry_points.txt
jps2sm-1.16.dist-info/top_level.txt
jps2sm-1.16.dist-info/RECORD
