Metadata-Version: 2.1
Name: jps2sm
Version: 1.16
Summary: Transfer data from JPS to SM
Home-page: https://github.com/damonjavert/jps2sm
Author: DamonJavert
Author-email: damonjavert@protonmail.com
License: GPLv3
Project-URL: Bug Tracker, https://github.com/damonjavert/jps2sm/issues
Project-URL: repository, https://github.com/damonjavert/jps2sm
Platform: unix
Platform: linux
Platform: osx
Platform: cygwin
Platform: win32
Classifier: Programming Language :: Python :: 3
Classifier: Programming Language :: Python :: 3 :: Only
Classifier: Programming Language :: Python :: 3.8
Classifier: Programming Language :: Python :: 3.9
Classifier: Programming Language :: Python :: 3.10
Classifier: Programming Language :: Python :: 3.11
Classifier: Programming Language :: Python :: 3.12
Classifier: Development Status :: 5 - Production/Stable
Classifier: License :: OSI Approved :: GNU General Public License v3 (GPLv3)
Classifier: Operating System :: OS Independent
Requires-Python: >=3.8
License-File: COPYING
Requires-Dist: beautifulsoup4 (>=4.8)
Requires-Dist: bs4 (>=0.0.1)
Requires-Dist: certifi (>=2019.9)
Requires-Dist: chardet (>=3.0)
Requires-Dist: html5lib (>=1.0)
Requires-Dist: idna (>=2.8)
Requires-Dist: pytz (>=2019.3)
Requires-Dist: requests (>=2.22)
Requires-Dist: six (>=1.12)
Requires-Dist: soupsieve (>=1.9)
Requires-Dist: sqlparse (>=0.3)
Requires-Dist: urllib3 (>=1.25)
Requires-Dist: webencodings (>=0.5)
Requires-Dist: pymediainfo (>=4.1)
Requires-Dist: torrent-parser (>=0.3)
Requires-Dist: humanfriendly (>=4.18)
Requires-Dist: pyunpack (>=0.2)
Requires-Dist: patool (>=1.12)
Requires-Dist: bencoding (>=0.2)
Requires-Dist: requestsloginsession (>=0.7)
Requires-Dist: datasize (>=1.0)
Requires-Dist: loguru (>=0.6)
